{
  "themes": ["Dark", "Light", "Grey"],
  "shared": [
    {
      "name": "ColorPalette",
      "type": "collection",
      "values": [
        {
          "type": "color",
          "name": "white",
          "value": "ffffffff"
        },
        {
          "type": "color",
          "name": "black",
          "value": "ff000000"
        },
        {
          "type": "color",
          "name": "red",
          "value": "ffff0000"
        },
        {
          "name": "NestedColorPalette",
          "type": "collection",
          "values": [
            {
              "type": "color",
              "name": "white",
              "value": "ff04ffff"
            },
            {
              "type": "color",
              "name": "black",
              "value": "ff009300"
            }

          ]
        }

      ]
    }

  ],
  "specific": [
    {
      "name": "TextEmphasis",
      "type": "collection",
      "values": [
        {
          "name": "white",
          "type": "color",
          "value": "ff0f0fff"
        },
        {
          "name": "black",
          "type": "color",
          "value": "ff89503d"
        }
      ]
    }
  ]
}